robotmk/__init__.py
robotmk/emitter.py
robotmk/logger.py
robotmk/main.py
robotmk/cli/cli.py
robotmk/cli/defaultgroup.py
robotmk/config/__init__.py
robotmk/config/config.py
robotmk/config/yml.py
robotmk/context/__init__.py
robotmk/context/abstract.py
robotmk/context/context.py
robotmk/context/agent/__init__.py
robotmk/context/agent/agent.py
robotmk/context/agent/cli.py
robotmk/context/server/__init__.py
robotmk/context/server/cli.py
robotmk/context/server/server.py
robotmk/context/specialagent/__init__.py
robotmk/context/specialagent/cli.py
robotmk/context/specialagent/specialagent.py
robotmk/context/suite/__init__.py
robotmk/context/suite/cli.py
robotmk/context/suite/suite.py
robotmk/context/suite/strategies/__init__.py
robotmk/context/suite/strategies/run.py
robotmk/context/suite/target/__init__.py
robotmk/context/suite/target/abstract.py
robotmk/context/suite/target/remote.py
robotmk/context/suite/target/target_factory.py
robotmk/context/suite/target/local/abstract.py
robotmk/context/suite/target/local/rcc.py
robotmk/context/suite/target/local/robotframework/__init__.py
robotmk/context/suite/target/local/robotframework/retry.py
robotmk/context/suite/target/local/robotframework/robotframework.py
robotmk/context/suite/target/local/robotframework/state.py
robotmk/executor/__init__.py
robotmk/executor/abstract.py
robotmk/executor/scheduler.py
robotmk/executor/sequencer.py
robotmk-0.0.126.dist-info/entry_points.txt
robotmk-0.0.126.dist-info/WHEEL
robotmk-0.0.126.dist-info/METADATA
robotmk-0.0.126.dist-info/RECORD
