Metadata-Version: 2.1
Name: robotmk
Version: 0.0.126
Summary: Robot Framework test execution and result parsing for Check_MK
Keywords: robotmk,checkmk,robotframework,automation,monitoring
Author-email: Simon Meggle <simon.meggle@elabit.de>
Classifier: License :: OSI Approved :: GNU General Public License v3 or later (GPLv3+)
Requires-Dist: click
Requires-Dist: psutil
Requires-Dist: apscheduler<=4
Requires-Dist: pyyaml
Requires-Dist: mergedeep
Requires-Dist: robotframework
Requires-Dist: loguru
Requires-Dist: schema
Requires-Dist: tabulate
